{
	"class" : {
		 },
	"instance" : {
		"actualContents" : "",
		"childSandblocksDo:" : "",
		"contents" : "",
		"contents:" : "",
		"continueInputInArgument:" : "",
		"currentTextMorph" : "",
		"deleteAround" : "",
		"deleteBeforeCursor" : "",
		"drawnColor" : "",
		"evaluate" : "",
		"fontToUse" : "",
		"hasColon" : "",
		"initialize" : "",
		"insertUnknownAfterAndInput:" : "",
		"isBinary" : "",
		"isFirstPart" : "",
		"isMessagePart" : "",
		"isUnary" : "",
		"keyStroke:" : "",
		"layoutCommands" : "",
		"messageSend" : "",
		"prefersNoBorder" : "",
		"printOn:" : "",
		"selectorContentsBeforeMe" : "",
		"startInputAt:replacingContents:" : "",
		"stopEditing:" : "",
		"symbols" : "",
		"textContents" : "",
		"updateSuggestions" : "",
		"useSuggestion:" : "",
		"wrapInCascade" : "",
		"wrapInMessageSend" : "",
		"wrapInMessageSend:" : "",
		"wrapWithWatch" : "" } }
